expiring_dict/__init__.py
expiring_dict/expiringdict.py
expiring_dict-1.1.2.dist-info/LICENSE
expiring_dict-1.1.2.dist-info/METADATA
expiring_dict-1.1.2.dist-info/WHEEL
expiring_dict-1.1.2.dist-info/top_level.txt
expiring_dict-1.1.2.dist-info/RECORD
