Metadata-Version: 2.2
Name: expiring-dict
Version: 1.1.2
Summary: Python dict with TTL support for auto-expiring caches
Home-page: https://github.com/dparker2/py-expiring-dict
Author: David Parker
Classifier: Programming Language :: Python :: 3
Classifier: License :: OSI Approved :: MIT License
Classifier: Operating System :: OS Independent
License-File: LICENSE
Requires-Dist: sortedcontainers
Dynamic: author
Dynamic: classifier
Dynamic: description
Dynamic: description-content-type
Dynamic: home-page
Dynamic: requires-dist
Dynamic: summary
